mcp_pped/__init__.py
mcp_pped/__main__.py
mcp_pped/server.py
mcp_pped-0.1.0.dist-info/METADATA
mcp_pped-0.1.0.dist-info/WHEEL
mcp_pped-0.1.0.dist-info/entry_points.txt
mcp_pped-0.1.0.dist-info/top_level.txt
mcp_pped-0.1.0.dist-info/RECORD
