Metadata-Version: 2.4
Name: mcp-pped
Version: 0.1.0
Requires-Python: >=3.10
Requires-Dist: build>=1.2.2.post1
Requires-Dist: mcp[cli]>=1.14.1
Requires-Dist: twine>=6.2.0
Requires-Dist: ultralytics>=5.14.3
Requires-Dist: sahi>=0.11.34
